cam_calib/__init__.py
cam_calib/cam_calib.py
camcalib/__init__.py
camcalib/camcalib.py
camcalib-1.0.5.dist-info/LICENSE
camcalib-1.0.5.dist-info/METADATA
camcalib-1.0.5.dist-info/WHEEL
camcalib-1.0.5.dist-info/top_level.txt
camcalib-1.0.5.dist-info/RECORD
