Metadata-Version: 2.1
Name: camcalib
Version: 1.0.5
Summary: A wrapper around the main functionalities offered by OpenCV for camera calibration for cleaner and maintainable calibration routines.
Home-page: https://github.com/AND2797/camera_calib
Author: Aditya Narayan Das
Author-email: aditya.das2797@gmail.com
License: MIT
Platform: UNKNOWN
Requires-Dist: numpy
Requires-Dist: opencv-contrib-python
Requires-Dist: opencv-python
Requires-Dist: tqdm
